albumr/__init__.py
albumr/__version__.py
albumr/albumr.py
albumr-1.0.9.dist-info/LICENSE.txt
albumr-1.0.9.dist-info/METADATA
albumr-1.0.9.dist-info/WHEEL
albumr-1.0.9.dist-info/entry_points.txt
albumr-1.0.9.dist-info/top_level.txt
albumr-1.0.9.dist-info/RECORD
