Metadata-Version: 2.1
Name: albumr
Version: 1.0.9
Summary: Imgur album downloader
Home-page: https://github.com/nkouevda/albumr
Author: Nikita Kouevda
Author-email: nkouevda@gmail.com
License: MIT
Platform: UNKNOWN
Requires-Dist: argparse-extensions
Requires-Dist: requests
Requires-Dist: six
